{
    "AX": {
        "error": 0.006426230210212246,
        "error_type": "SEM",
        "filter_outliers_dict": {
            "filter_outliers": true,
            "iterations": 1,
            "std_devs": 2,
            "use_standard_deviation_filtering": false
        },
        "fit": "Average",
        "fn": 56,
        "include_baseline_error": false,
        "n": 60,
        "outlier_excluded": [
            17,
            35,
            37,
            14
        ],
        "reviewed": true,
        "user_excluded": [],
        "value": -0.15685670131019183
    },
    "CDD": {
        "error": 2.2159760366669458e-05,
        "error_type": "SEM",
        "filter_outliers_dict": {
            "filter_outliers": true,
            "iterations": 1,
            "std_devs": 10,
            "use_standard_deviation_filtering": false
        },
        "fit": "Average",
        "fn": 60,
        "include_baseline_error": false,
        "n": 60,
        "outlier_excluded": [],
        "reviewed": true,
        "user_excluded": [],
        "value": 0.00016538948402740062
    },
    "H1": {
        "error": 0.005356405366202573,
        "error_type": "SEM",
        "filter_outliers_dict": {
            "filter_outliers": true,
            "iterations": 1,
            "std_devs": 2,
            "use_standard_deviation_filtering": false
        },
        "fit": "Average",
        "fn": 57,
        "include_baseline_error": false,
        "n": 60,
        "outlier_excluded": [
            12,
            21,
            14
        ],
        "reviewed": true,
        "user_excluded": [],
        "value": 0.02334615384716655
    },
    "H2": {
        "error": 0.0024961350440424477,
        "error_type": "SEM",
        "filter_outliers_dict": {
            "filter_outliers": true,
            "iterations": 1,
            "std_devs": 2
        },
        "fit": "average",
        "value": -0.0029946641450738277
    },
    "L1": {
        "error": 0.003078610560338055,
        "error_type": "SEM",
        "filter_outliers_dict": {
            "filter_outliers": true,
            "iterations": 1,
            "std_devs": 2,
            "use_standard_deviation_filtering": false
        },
        "fit": "Average",
        "fn": 57,
        "include_baseline_error": false,
        "n": 60,
        "outlier_excluded": [
            24,
            22,
            23
        ],
        "reviewed": true,
        "user_excluded": [],
        "value": 0.05179644369503908
    },
    "L2": {
        "error": 0.006157861951807328,
        "error_type": "SEM",
        "filter_outliers_dict": {
            "filter_outliers": true,
            "iterations": 1,
            "std_devs": 2,
            "use_standard_deviation_filtering": false
        },
        "fit": "Average",
        "fn": 58,
        "include_baseline_error": false,
        "n": 60,
        "outlier_excluded": [
            13,
            45
        ],
        "reviewed": true,
        "user_excluded": [],
        "value": -0.05895354451435008
    }
}